setup.py
ab_biga/Binomialdistribution.py
ab_biga/GaussianDistribution.py
ab_biga/GeneralDistribution.py
ab_biga/__init__.py
ab_biga.egg-info/PKG-INFO
ab_biga.egg-info/SOURCES.txt
ab_biga.egg-info/dependency_links.txt
ab_biga.egg-info/not-zip-safe
ab_biga.egg-info/top_level.txt