Metadata-Version: 2.1
Name: ab-biga
Version: 1.0
Summary: Gaussian distrbutions
Home-page: UNKNOWN
Author: Abrham Gebregiorgis
Author-email: abrhamgg@gmail.com
License: UNKNOWN
Platform: UNKNOWN
